{
    "key": "group_650d15e689b38",
    "title": "Post Featured",
    "fields": [
        {
            "key": "field_650d15f6b377c",
            "label": "Select Cut",
            "name": "select_cut",
            "type": "select",
            "instructions": "",
            "required": 0,
            "conditional_logic": 0,
            "wrapper": {
                "width": "",
                "class": "",
                "id": ""
            },
            "choices": {
                "both": "Both",
                "top": "Top",
                "bottom": "Bottom"
            },
            "default_value": false,
            "allow_null": 0,
            "multiple": 0,
            "ui": 0,
            "return_format": "value",
            "ajax": 0,
            "placeholder": ""
        },
        {
            "key": "field_650d160cb377d",
            "label": "Image Banner",
            "name": "image_banner",
            "type": "image",
            "instructions": "",
            "required": 0,
            "conditional_logic": 0,
            "wrapper": {
                "width": "",
                "class": "",
                "id": ""
            },
            "return_format": "array",
            "preview_size": "medium",
            "library": "all",
            "min_width": "",
            "min_height": "",
            "min_size": "",
            "max_width": "",
            "max_height": "",
            "max_size": "",
            "mime_types": ""
        },
        {
            "key": "field_650d161db377e",
            "label": "Post Featured 01",
            "name": "post_featured_01",
            "type": "post_object",
            "instructions": "",
            "required": 0,
            "conditional_logic": 0,
            "wrapper": {
                "width": "",
                "class": "",
                "id": ""
            },
            "post_type": [
                "post"
            ],
            "taxonomy": "",
            "allow_null": 0,
            "multiple": 0,
            "return_format": "object",
            "ui": 1
        },
        {
            "key": "field_650d1663b377f",
            "label": "Post Featured 02",
            "name": "post_featured_02",
            "type": "post_object",
            "instructions": "",
            "required": 0,
            "conditional_logic": 0,
            "wrapper": {
                "width": "",
                "class": "",
                "id": ""
            },
            "post_type": [
                "post"
            ],
            "taxonomy": "",
            "allow_null": 0,
            "multiple": 0,
            "return_format": "object",
            "ui": 1
        },
        {
            "key": "field_650d16a8b3780",
            "label": "Post Featured 03",
            "name": "post_featured_03",
            "type": "post_object",
            "instructions": "",
            "required": 0,
            "conditional_logic": 0,
            "wrapper": {
                "width": "",
                "class": "",
                "id": ""
            },
            "post_type": [
                "post"
            ],
            "taxonomy": "",
            "allow_null": 0,
            "multiple": 0,
            "return_format": "object",
            "ui": 1
        },
        {
            "key": "field_650d16c1b3781",
            "label": "Post Featured 04",
            "name": "post_featured_04",
            "type": "post_object",
            "instructions": "",
            "required": 0,
            "conditional_logic": 0,
            "wrapper": {
                "width": "",
                "class": "",
                "id": ""
            },
            "post_type": [
                "post"
            ],
            "taxonomy": "",
            "allow_null": 0,
            "multiple": 0,
            "return_format": "object",
            "ui": 1
        },
        {
            "key": "field_650d16e3b3782",
            "label": "Post Featured 05",
            "name": "post_featured_05",
            "type": "post_object",
            "instructions": "",
            "required": 0,
            "conditional_logic": 0,
            "wrapper": {
                "width": "",
                "class": "",
                "id": ""
            },
            "post_type": [
                "post"
            ],
            "taxonomy": "",
            "allow_null": 0,
            "multiple": 0,
            "return_format": "object",
            "ui": 1
        }
    ],
    "location": [
        [
            {
                "param": "block",
                "operator": "==",
                "value": "acf\/post-featured"
            }
        ]
    ],
    "menu_order": 0,
    "position": "normal",
    "style": "default",
    "label_placement": "top",
    "instruction_placement": "label",
    "hide_on_screen": [
        "the_content"
    ],
    "active": true,
    "description": "",
    "show_in_rest": 0,
    "modified": 1695356658
}